CHANGES.rst
LICENSE
MANIFEST.in
README.rst
setup.py
SQLAlchemy_Defaults.egg-info/PKG-INFO
SQLAlchemy_Defaults.egg-info/SOURCES.txt
SQLAlchemy_Defaults.egg-info/dependency_links.txt
SQLAlchemy_Defaults.egg-info/not-zip-safe
SQLAlchemy_Defaults.egg-info/requires.txt
SQLAlchemy_Defaults.egg-info/top_level.txt
docs/Makefile
docs/conf.py
docs/index.rst
docs/make.bat
sqlalchemy_defaults/__init__.py
tests/__init__.py
tests/test_boolean_defaults.py
tests/test_datetime_defaults.py
tests/test_float_defaults.py
tests/test_integer_defaults.py
tests/test_lazy_configurable.py
tests/test_numeric_defaults.py
tests/test_string_defaults.py